Workbook
Name aporte: AUREA!$D$19
Name patrimonio: AUREA!$D$22
Name qtd_anos: AUREA!$D$20
Name Redimento_carteira: AUREA!$D$15
Name soma: AUREA!$D$23
Name taxa_mensal: AUREA!$D$21

Sheet AUREA
B13: CONFIGURAÇÕES
B14: Salário | D14: 5000
B15: Rendimento Carteira | D15: 0.0089
B16: Sugestão de Investimento | D16: =D14*30% -> 1500
B18: INVESTIMENTO MENSAL
B19: Quanto investir por mês? | D19: 200
B20: Por quantos anos? | D20: 5
A21: 2 | B21: Taxa de rendimento mensal? | D21: 0.01079
A22: 5 | B22: Patrimônio acumulado? | D22: =FV(taxa_mensal,qtd_anos*12,aporte*-1) -> 16755.383
A23: 10 | B23: Dividendos mensais? | D23: =(D22*1%) -> 167.55383
A24: 20
A25: 30 | B25: CENÁRIOS | D25: DIVIDENDO
B26: Quanto em 2 anos? | C26: =FV($D$21,$A21*12,$D$19*-1) -> 5445.5255 | D26: =(C26*Redimento_carteira) -> 48.465177
B27: Quanto em 5 anos? | C27: =FV($D$21,$A22*12,$D$19*-1) -> 16755.383 | D27: =(C27*Redimento_carteira) -> 149.12291
B28: Quanto em 10 anos? | C28: =FV($D$21,$A23*12,$D$19*-1) -> 48656.843 | D28: =(C28*Redimento_carteira) -> 433.0459
B29: Quanto em 20 anos? | C29: =FV($D$21,$A24*12,$D$19*-1) -> 225039.68 | D29: =(C29*Redimento_carteira) -> 2002.8532
B30: Quanto em 30 anos? | C30: =FV($D$21,$A25*12,$D$19*-1) -> 864433.93 | D30: =(C30*Redimento_carteira) -> 7693.462
B33: Perfil | C33: Moderado
B34: VALOR A SER INVESTIDO POR MÊS | C34: =aporte -> 200
B36: TIPO DE FII | C36: Percentual Sugerido | D36: Valores
B37: PAPEL | C37: =VLOOKUP($C$33&"-"&B37,Planilha2!$A:$D,4,FALSE) -> 0.32 | D37: =C37*$C$34 -> 64
B38: TIJOLO | C38: =VLOOKUP($C$33&"-"&B38,Planilha2!A:D,4,FALSE) -> 0.35 | D38: =C38*$C$34 -> 70
B39: HÍBRIDOS | C39: =VLOOKUP($C$33&"-"&B39,Planilha2!A:D,4,FALSE) -> 0.08 | D39: =C39*$C$34 -> 16
B40: FOFs | C40: =VLOOKUP($C$33&"-"&B40,Planilha2!A:D,4,FALSE) -> 0.05 | D40: =C40*$C$34 -> 10
B41: DESENVOLVIMENTO | C41: =VLOOKUP($C$33&"-"&B41,Planilha2!A:D,4,FALSE) -> 0.1 | D41: =C41*$C$34 -> 20
B42: HOTELARIAS | C42: =VLOOKUP($C$33&"-"&B42,Planilha2!A:D,4,FALSE) -> 0.1 | D42: =C42*$C$34 -> 20
D43: =SUM(D37:D42) -> 200

Sheet Planilha2
A4: CHAVE | B4: PERFIL | C4: TIPO DE FII | D4: %
A5: =(B5&"-"&C5) -> Conservador-PAPEL | B5: Conservador | C5: PAPEL | D5: 0.3 | H5: %
A6: =(B6&"-"&C6) -> Conservador-TIJOLO | B6: Conservador | C6: TIJOLO | D6: 0.5 | G6: Moderado-TIJOLO | H6: =VLOOKUP(G6,$A:$D,4,FALSE) -> 0.35
A7: =(B7&"-"&C7) -> Conservador-HÍBRIDOS | B7: Conservador | C7: HÍBRIDOS | D7: 0.1
A8: =(B8&"-"&C8) -> Conservador-FOFs | B8: Conservador | C8: FOFs | D8: 0.1
A9: =(B9&"-"&C9) -> Conservador-DESENVOLVIMENTO | B9: Conservador | C9: DESENVOLVIMENTO | D9: 0
A10: =(B10&"-"&C10) -> Conservador-HOTELARIAS | B10: Conservador | C10: HOTELARIAS | D10: 0
A11: =(B11&"-"&C11) -> Moderado-PAPEL | B11: Moderado | C11: PAPEL | D11: 0.32
A12: =(B12&"-"&C12) -> Moderado-TIJOLO | B12: Moderado | C12: TIJOLO | D12: 0.35
A13: =(B13&"-"&C13) -> Moderado-HÍBRIDOS | B13: Moderado | C13: HÍBRIDOS | D13: 0.08
A14: =(B14&"-"&C14) -> Moderado-FOFs | B14: Moderado | C14: FOFs | D14: 0.05
A15: =(B15&"-"&C15) -> Moderado-DESENVOLVIMENTO | B15: Moderado | C15: DESENVOLVIMENTO | D15: 0.1
A16: =(B16&"-"&C16) -> Moderado-HOTELARIAS | B16: Moderado | C16: HOTELARIAS | D16: 0.1
A17: =(B17&"-"&C17) -> Agressivo-PAPEL | B17: Agressivo | C17: PAPEL | D17: 0.5
A18: =(B18&"-"&C18) -> Agressivo-TIJOLO | B18: Agressivo | C18: TIJOLO | D18: 0.1
... A22: =(B22&"-"&C22) -> Agressivo-HOTELARIAS | B22: Agressivo | C22: HOTELARIAS | D22: 0.1
